warsaw_data_api/__init__.py
warsaw_data_api/exceptions.py
warsaw_data_api/session.py
warsaw_data_api/ztm/__init__.py
warsaw_data_api/ztm/models.py
warsaw_data_api-0.5.3.dist-info/LICENSE.md
warsaw_data_api-0.5.3.dist-info/METADATA
warsaw_data_api-0.5.3.dist-info/WHEEL
warsaw_data_api-0.5.3.dist-info/RECORD
