Metadata-Version: 2.1
Name: warsaw-data-api
Version: 0.5.3
Summary: Warsaw data python api
Home-page: https://github.com/radekwielonski/warsaw-data-api
License: MIT
Author: Radoslaw Wielonski
Author-email: radek.wielonski@gmail.com
Requires-Python: >=3.7,<4.0
Classifier: License :: OSI Approved :: MIT License
Classifier: Programming Language :: Python :: 3
Classifier: Programming Language :: Python :: 3.7
Classifier: Programming Language :: Python :: 3.8
Classifier: Programming Language :: Python :: 3.9
Classifier: Programming Language :: Python :: 3.10
Classifier: Programming Language :: Python :: 3.11
Classifier: Programming Language :: Python :: 3.12
Requires-Dist: requests (>=2.30.0,<3.0.0)
